README.rst
setup.py
src/pwman/__init__.py
src/pwman/pwman.py
src/pwman/tool.py
src/pwman.egg-info/PKG-INFO
src/pwman.egg-info/SOURCES.txt
src/pwman.egg-info/dependency_links.txt
src/pwman.egg-info/entry_points.txt
src/pwman.egg-info/requires.txt
src/pwman.egg-info/top_level.txt