Metadata-Version: 1.0
Name: pwman
Version: 2.0.0
Summary: Simple command line client to manage nginx basic auth files. Think htpasswd (but not quite) as lib. Writes SSHA hashes.
Home-page: http://felixhummel.de/pwman
Author: Felix Hummel
Author-email: felix@felixhummel.de
License: UNKNOWN
Platform: UNKNOWN
